{
  "moves": [
    {
      "notation": "1",
      "hit_level": "h",
      "damage": "9",
      "speed": "10",
      "on_block": "+1",
      "on_hit": "+8",
      "on_ch": "+8"
    },
    {
      "notation": "1, 2",
      "hit_level": "h, h",
      "damage": "9,12",
      "speed": "10",
      "on_block": "-4",
      "on_hit": "+4",
      "on_ch": "+4"
    },
    {
      "notation": "1, 2, 3",
      "hit_level": "h, h, h, (SCR)",
      "damage": "9,12,16",
      "speed": "10",
      "on_block": "-1",
      "on_hit": "+8",
      "on_ch": "+8"
    },
    {
      "notation": "1, 2, 3, b",
      "hit_level": "h, h, h",
      "damage": "9,12,16",
      "speed": "10",
      "on_block": "-9",
      "on_hit": "0",
      "on_ch": "0"
    },
    {
      "notation": "1, 3",
      "hit_level": "h, h, (SCR)",
      "damage": "9,18",
      "speed": "10",
      "on_block": "-4",
      "on_hit": "+5",
      "on_ch": "+5"
    },
    {
      "notation": "1, 3, b",
      "hit_level": "h, h",
      "damage": "9,18",
      "speed": "10",
      "on_block": "-8",
      "on_hit": "+1",
      "on_ch": "+1"
    },
    {
      "notation": "1, 4",
      "hit_level": "h, m, (TRT)",
      "damage": "9,20",
      "speed": "10",
      "on_block": "-8",
      "on_hit": "-1",
      "on_ch": "KND"
    },
    {
      "notation": "2",
      "hit_level": "h",
      "damage": "13",
      "speed": "10",
      "on_block": "-7",
      "on_hit": "-1",
      "on_ch": "-1"
    },
    {
      "notation": "2, 1",
      "hit_level": "h, m",
      "damage": "13,14",
      "speed": "10",
      "on_block": "-6~-4 OC",
      "on_hit": "+2~+4 OC",
      "on_ch": "+2~+4 OC"
    },
    {
      "notation": "2, 1, 3",
      "hit_level": "h, m, l, (MNT)",
      "damage": "13,14,27",
      "speed": "10",
      "on_block": "-17",
      "on_hit": "KND",
      "on_ch": "KND"
    },
    {
      "notation": "2, 1, 3, d (Cancel)",
      "hit_level": "h, m, (MNT)",
      "damage": "12,13",
      "speed": "10",
      "on_block": "-17~-15 OC",
      "on_hit": "-9~-7 OC",
      "on_ch": "-9~-7 OC"
    },
    {
      "notation": "2, 2",
      "hit_level": "h, m",
      "damage": "13,16",
      "speed": "10",
      "on_block": "-12",
      "on_hit": "-1",
      "on_ch": "+4"
    },
    {
      "notation": "2, 2, 1+2",
      "hit_level": "h, m, mmm",
      "damage": "13,16,9,14,27",
      "speed": "10",
      "on_block": "-9~-8",
      "on_hit": "KND",
      "on_ch": "KND"
    },
    {
      "notation": "2, 2, 1+2 (Fifth hit only)",
      "hit_level": "h, m, mmm",
      "damage": "13,16,9,14,27",
      "speed": "10",
      "on_block": "-9~-8",
      "on_hit": "+4~+5 OC",
      "on_ch": "KND"
    },
    {
      "notation": "3",
      "hit_level": "h, (SCR)",
      "damage": "22",
      "speed": "13",
      "on_block": "-1",
      "on_hit": "+8",
      "on_ch": "+8"
    },
    {
      "notation": "3, b",
      "hit_level": "h",
      "damage": "22",
      "speed": "13",
      "on_block": "-8",
      "on_hit": "+1",
      "on_ch": "+1"
    },
    {
      "notation": "1+2",
      "hit_level": "m",
      "damage": "27",
      "speed": "16~17",
      "on_block": "-12~-11",
      "on_hit": "+4~+5",
      "on_ch": "CS"
    },
    {
      "notation": "1+2, 4",
      "hit_level": "m, m",
      "damage": "27,16",
      "speed": "16~17",
      "on_block": "-10",
      "on_hit": "+1",
      "on_ch": "+6"
    },
    {
      "notation": "1+2, 4, 4",
      "hit_level": "m, m, m",
      "damage": "27,16,35",
      "speed": "16~17",
      "on_block": "-11",
      "on_hit": "KND",
      "on_ch": "KND"
    },
    {
      "notation": "f+2",
      "hit_level": "m",
      "damage": "22",
      "speed": "19",
      "on_block": "-18",
      "on_hit": "-6",
      "on_ch": "CS"
    },
    {
      "notation": "f+2, 3",
      "hit_level": "m, h, (SCR)",
      "damage": "22,16",
      "speed": "19",
      "on_block": "-1",
      "on_hit": "+8",
      "on_ch": "+8"
    },
    {
      "notation": "f+2, 3, b",
      "hit_level": "m, h",
      "damage": "22,16",
      "speed": "19",
      "on_block": "-9",
      "on_hit": "0",
      "on_ch": "0"
    },
    {
      "notation": "f+2, 3, 4",
      "hit_level": "m, h, m",
      "damage": "22,16,33",
      "speed": "19",
      "on_block": "-18",
      "on_hit": "KND",
      "on_ch": "KND"
    },
    {
      "notation": "f+3",
      "hit_level": "h, (SCR)",
      "damage": "37",
      "speed": "21",
      "on_block": "0 OS",
      "on_hit": "KND",
      "on_ch": "KND"
    },
    {
      "notation": "f+3, b",
      "hit_level": "h",
      "damage": "37",
      "speed": "21",
      "on_block": "-1 OS",
      "on_hit": "KND",
      "on_ch": "KND"
    },
    {
      "notation": "f+4",
      "hit_level": "h",
      "damage": "24",
      "speed": "14",
      "on_block": "-8",
      "on_hit": "KND",
      "on_ch": "KND"
    },
    {
      "notation": "f+1+2",
      "hit_level": "m",
      "damage": "32",
      "speed": "19",
      "on_block": "-10",
      "on_hit": "KND",
      "on_ch": "KND"
    },
    {
      "notation": "d/f+1",
      "hit_level": "m",
      "damage": "14",
      "speed": "13~14",
      "on_block": "-5~-4",
      "on_hit": "+7~+8",
      "on_ch": "+7~+8"
    },
    {
      "notation": "d/f+1, 2",
      "hit_level": "m, m",
      "damage": "14,21",
      "speed": "13~14",
      "on_block": "-15",
      "on_hit": "+1",
      "on_ch": "+1"
    },
    {
      "notation": "d/f+1, 2, 1",
      "hit_level": "m, m, m",
      "damage": "14,21,27",
      "speed": "13~14",
      "on_block": "-14",
      "on_hit": "+8",
      "on_ch": "KND"
    },
    {
      "notation": "d/f+1, 4",
      "hit_level": "m, h",
      "damage": "14,24",
      "speed": "13~14",
      "on_block": "-6",
      "on_hit": "-1",
      "on_ch": "-1"
    },
    {
      "notation": "d/f+2",
      "hit_level": "m",
      "damage": "17",
      "speed": "16~17",
      "on_block": "-12~-11",
      "on_hit": "Launch (JG?)",
      "on_ch": "Launch (JG?)"
    },
    {
      "notation": "d/f+3",
      "hit_level": "m, (SCR)",
      "damage": "20",
      "speed": "14",
      "on_block": "-5",
      "on_hit": "+1",
      "on_ch": "+6"
    },
    {
      "notation": "d/f+3, b",
      "hit_level": "m",
      "damage": "20",
      "speed": "14",
      "on_block": "-10",
      "on_hit": "-4",
      "on_ch": "+1"
    },
    {
      "notation": "d/f+3, 4",
      "hit_level": "m, h",
      "damage": "20,22",
      "speed": "14",
      "on_block": "-6",
      "on_hit": "+9",
      "on_ch": "CS"
    },
    {
      "notation": "d/f+3, d+4",
      "hit_level": "m, l",
      "damage": "20,20",
      "speed": "14",
      "on_block": "-17",
      "on_hit": "-2 OC",
      "on_ch": "-2 OC"
    },
    {
      "notation": "d/f+3, d+4, D",
      "hit_level": "m, l",
      "damage": "20,20",
      "speed": "14 RC",
      "on_block": "-17",
      "on_hit": "-2 OC",
      "on_ch": "-2 OC"
    },
    {
      "notation": "d/f+4",
      "hit_level": "m",
      "damage": "18",
      "speed": "14",
      "on_block": "-13",
      "on_hit": "-3",
      "on_ch": "+3"
    },
    {
      "notation": "d/f+4, 1",
      "hit_level": "m, m",
      "damage": "18,29",
      "speed": "14",
      "on_block": "-12~-11",
      "on_hit": "+8~+9",
      "on_ch": "CS"
    },
    {
      "notation": "d/f+4, 1, d (Cancel)",
      "hit_level": "m",
      "damage": "18",
      "speed": "14 RC",
      "on_block": "-18",
      "on_hit": "-8",
      "on_ch": "-2"
    },
    {
      "notation": "d/f+1+2",
      "hit_level": "m (TC)",
      "damage": "27",
      "speed": "36",
      "on_block": "-10",
      "on_hit": "CS",
      "on_ch": "CS"
    },
    {
      "notation": "d+1",
      "hit_level": "m",
      "damage": "17",
      "speed": "12",
      "on_block": "-16",
      "on_hit": "-8 OC",
      "on_ch": "-3 OC"
    },
    {
      "notation": "d+1, 1",
      "hit_level": "m, m",
      "damage": "17,20",
      "speed": "12",
      "on_block": "-13",
      "on_hit": "KND",
      "on_ch": "CS"
    },
    {
      "notation": "d+2",
      "hit_level": "m",
      "damage": "21",
      "speed": "19~20",
      "on_block": "-16~-15 OC",
      "on_hit": "-3~-2 OC",
      "on_ch": "KND"
    },
    {
      "notation": "d+2, 4",
      "hit_level": "m, m, (MNT)",
      "damage": "21,17",
      "speed": "19~20",
      "on_block": "-25",
      "on_hit": "-7",
      "on_ch": "-7 OC"
    },
    {
      "notation": "d+2, 4, D",
      "hit_level": "m, m, (TRT)",
      "damage": "21,17",
      "speed": "19~20",
      "on_block": "-22",
      "on_hit": "-4",
      "on_ch": "-4 OC"
    },
    {
      "notation": "d+2, 4, 3",
      "hit_level": "m, m, m",
      "damage": "21,17,20",
      "speed": "19~20",
      "on_block": "-14~-13",
      "on_hit": "KND",
      "on_ch": "KND"
    },
    {
      "notation": "d+3",
      "hit_level": "l (TC)",
      "damage": "22",
      "speed": "22 RC",
      "on_block": "-13",
      "on_hit": "+4 OC",
      "on_ch": "KND"
    },
    {
      "notation": "d+3, D",
      "hit_level": "l (TC), (MNT)",
      "damage": "22",
      "speed": "22",
      "on_block": "-16",
      "on_hit": "+1 OC",
      "on_ch": "KND"
    },
    {
      "notation": "d+4",
      "hit_level": "l",
      "damage": "10",
      "speed": "17",
      "on_block": "-19",
      "on_hit": "-3",
      "on_ch": "+18 GB"
    },
    {
      "notation": "d+4, 3",
      "hit_level": "l, h",
      "damage": "10,13",
      "speed": "17",
      "on_block": "-6",
      "on_hit": "Launch (JG?)",
      "on_ch": "Launch (JG?)"
    },
    {
      "notation": "d/b+2",
      "hit_level": "m",
      "damage": "21",
      "speed": "13~14",
      "on_block": "-9~-8",
      "on_hit": "+3~+4",
      "on_ch": "KND"
    },
    {
      "notation": "d/b+3",
      "hit_level": "l, (SCR)",
      "damage": "20",
      "speed": "18",
      "on_block": "-8",
      "on_hit": "+3",
      "on_ch": "+3"
    },
    {
      "notation": "d/b+3, b",
      "hit_level": "l",
      "damage": "20",
      "speed": "18",
      "on_block": "-11",
      "on_hit": "0",
      "on_ch": "0"
    },
    {
      "notation": "d/b+4 or FC+d/b+4",
      "hit_level": "l (TC)",
      "damage": "18",
      "speed": "21",
      "on_block": "-13",
      "on_hit": "-4",
      "on_ch": "+3"
    },
    {
      "notation": "d/b+4, D",
      "hit_level": "l (TC), (MNT)",
      "damage": "18",
      "speed": "21",
      "on_block": "-14",
      "on_hit": "-5",
      "on_ch": "+2"
    },
    {
      "notation": "d/b+4, 2",
      "hit_level": "l (TC), m",
      "damage": "18,22",
      "speed": "21",
      "on_block": "-13~-11",
      "on_hit": "Launch(JG?)",
      "on_ch": "Launch(JG?)"
    },
    {
      "notation": "d/b+1+2",
      "hit_level": "l (TC), (MNT)",
      "damage": "22",
      "speed": "28",
      "on_block": "-16",
      "on_hit": "KND",
      "on_ch": "KND"
    },
    {
      "notation": "d/b+1+2, 1+2",
      "hit_level": "l (TC), m",
      "damage": "22,27",
      "speed": "28",
      "on_block": "-14",
      "on_hit": "CS",
      "on_ch": "CS"
    },
    {
      "notation": "b+1",
      "hit_level": "m",
      "damage": "25",
      "speed": "18",
      "on_block": "-11",
      "on_hit": "+5",
      "on_ch": "CS"
    },
    {
      "notation": "b+2",
      "hit_level": "h",
      "damage": "29",
      "speed": "22",
      "on_block": "-8",
      "on_hit": "+7",
      "on_ch": "CS"
    },
    {
      "notation": "b+3",
      "hit_level": "m",
      "damage": "33",
      "speed": "24~25",
      "on_block": "-3~-2 OC",
      "on_hit": "KND",
      "on_ch": "KND"
    },
    {
      "notation": "b+4",
      "hit_level": "m",
      "damage": "24",
      "speed": "22",
      "on_block": "-9",
      "on_hit": "-3",
      "on_ch": "-3"
    },
    {
      "notation": "b+4, 4",
      "hit_level": "m, m",
      "damage": "24,29",
      "speed": "22",
      "on_block": "-14",
      "on_hit": "KND",
      "on_ch": "KND"
    },
    {
      "notation": "b+1+2",
      "hit_level": "l",
      "damage": "16",
      "speed": "16",
      "on_block": "-22",
      "on_hit": "-7 OC",
      "on_ch": "-7 OC"
    },
    {
      "notation": "b+2+3",
      "hit_level": "!",
      "damage": "54",
      "speed": "64",
      "on_block": "CS",
      "on_hit": "CS",
      "on_ch": "CS"
    },
    {
      "notation": "u/f+1",
      "hit_level": "h",
      "damage": "27",
      "speed": "19",
      "on_block": "+2",
      "on_hit": "+7",
      "on_ch": "KND"
    },
    {
      "notation": "u/b+3",
      "hit_level": "m (TJ)",
      "damage": "25",
      "speed": "22",
      "on_block": "-17",
      "on_hit": "-6",
      "on_ch": "-6"
    },
    {
      "notation": "u or u/f+3",
      "hit_level": "m (TJ)",
      "damage": "33",
      "speed": "22",
      "on_block": "-8",
      "on_hit": "KND",
      "on_ch": "KND"
    },
    {
      "notation": "u/f+1+2",
      "hit_level": "m (TJ), (Special) (TC)(TRT)",
      "damage": "27",
      "speed": "21",
      "on_block": "-7",
      "on_hit": "+6",
      "on_ch": "CS"
    },
    {
      "notation": "f, F+2",
      "hit_level": "h",
      "damage": "40",
      "speed": "15(16~)",
      "on_block": "+1",
      "on_hit": "KND",
      "on_ch": "KND"
    },
    {
      "notation": "f, F+3",
      "hit_level": "m, (SCR)",
      "damage": "32",
      "speed": "20~21 (21~)",
      "on_block": "+4~+5",
      "on_hit": "+9~+10 OC",
      "on_ch": "KND"
    },
    {
      "notation": "f, F+3, B",
      "hit_level": "m",
      "damage": "32",
      "speed": "20~21 (21~)",
      "on_block": "+4~+5",
      "on_hit": "+9~+10SG",
      "on_ch": "KND"
    },
    {
      "notation": "f, F+3, 1",
      "hit_level": "m, m",
      "damage": "32,32",
      "speed": "20~21 (21~)",
      "on_block": "-16",
      "on_hit": "KND",
      "on_ch": "KND"
    },
    {
      "notation": "f, F+4",
      "hit_level": "m (TJ)",
      "damage": "29",
      "speed": "17~18 (18~)",
      "on_block": "-8~-7",
      "on_hit": "KND",
      "on_ch": "KND"
    },
    {
      "notation": "f, F+3+4",
      "hit_level": "mm (TJ)",
      "damage": "13,28",
      "speed": "21,30~33 (22~)",
      "on_block": "-11~-8",
      "on_hit": "KND",
      "on_ch": "KND"
    },
    {
      "notation": "f, F+3+4, D",
      "hit_level": "mm (TJ), (MNT)",
      "damage": "13,28",
      "speed": "21,30~33 (22~)",
      "on_block": "-12~-9",
      "on_hit": "KND",
      "on_ch": "KND"
    },
    {
      "notation": "f, f, f+3 or WR+3",
      "hit_level": "m (TJ)",
      "damage": "40",
      "speed": "23~30 (26~)",
      "on_block": "+6~+13 GB",
      "on_hit": "KND",
      "on_ch": "KND"
    },
    {
      "notation": "WR+4",
      "hit_level": "l",
      "damage": "28",
      "speed": "14 RG",
      "on_block": "-40",
      "on_hit": "KND",
      "on_ch": "KND"
    },
    {
      "notation": "WR+4, U",
      "hit_level": "l, (Special)",
      "damage": "28",
      "speed": "14( RBT)",
      "on_block": "-52",
      "on_hit": "KND",
      "on_ch": "KND"
    },
    {
      "notation": "WR+4, D",
      "hit_level": "l, (TRT)",
      "damage": "28",
      "speed": "14 Air",
      "on_block": "-51",
      "on_hit": "KND",
      "on_ch": "KND"
    },
    {
      "notation": "WS+1",
      "hit_level": "m",
      "damage": "13",
      "speed": "15",
      "on_block": "-10",
      "on_hit": "+1",
      "on_ch": "+1"
    },
    {
      "notation": "WS+1, 2",
      "hit_level": "m, m",
      "damage": "13,18",
      "speed": "15",
      "on_block": "-13~-12",
      "on_hit": "Launch (JG?)(Launch)",
      "on_ch": "Launch (JG?)"
    },
    {
      "notation": "WS+2",
      "hit_level": "m (TC)",
      "damage": "27",
      "speed": "18",
      "on_block": "-14",
      "on_hit": "Launch (JG?)",
      "on_ch": "Launch (JG?)"
    },
    {
      "notation": "WS+2, d",
      "hit_level": "m (TC), (MNT)",
      "damage": "27",
      "speed": "18",
      "on_block": "-40",
      "on_hit": "Launch (JG?)",
      "on_ch": "Launch (JG?)"
    },
    {
      "notation": "WS+3",
      "hit_level": "h, (SCR)",
      "damage": "32",
      "speed": "16",
      "on_block": "+8",
      "on_hit": "KND",
      "on_ch": "KND"
    },
    {
      "notation": "WS+3, b",
      "hit_level": "h",
      "damage": "32",
      "speed": "16",
      "on_block": "-7",
      "on_hit": "KND",
      "on_ch": "KND"
    },
    {
      "notation": "FC+d/f+3",
      "hit_level": "l",
      "damage": "20",
      "speed": "23~24",
      "on_block": "-26~-25",
      "on_hit": "KND",
      "on_ch": "KND"
    },
    {
      "notation": "FC+d/f+3, d/b or D",
      "hit_level": "l, (MNT)",
      "damage": "20",
      "speed": "23~24",
      "on_block": null,
      "on_hit": "KND",
      "on_ch": "KND"
    },
    {
      "notation": "SS+1+2",
      "hit_level": "m",
      "damage": "29",
      "speed": "17(26~)",
      "on_block": "-2 OC",
      "on_hit": "+8 OC",
      "on_ch": "KND"
    },
    {
      "notation": "d+1+2 or From certain moves (to TRT)",
      "hit_level": "(Special) (TC)(TRT)",
      "damage": null,
      "speed": "Air",
      "on_block": null,
      "on_hit": null,
      "on_ch": null
    },
    {
      "notation": "d+1+2, d/b or u/b or u or U/F (Cancel)",
      "hit_level": "(Special)",
      "damage": null,
      "speed": null,
      "on_block": null,
      "on_hit": null,
      "on_ch": null
    },
    {
      "notation": "TRT 1",
      "hit_level": "l, (TRT)",
      "damage": "14",
      "speed": "18 Air(48~)",
      "on_block": "-11",
      "on_hit": "+5",
      "on_ch": "KND"
    },
    {
      "notation": "TRT 2",
      "hit_level": "m",
      "damage": "32",
      "speed": "34~36 (64~)",
      "on_block": "-9~-7",
      "on_hit": "Launch (JG?)",
      "on_ch": "Launch (JG?)"
    },
    {
      "notation": "TRT 3",
      "hit_level": "m, (TRT)",
      "damage": "21",
      "speed": "14 Air(44~)",
      "on_block": "-7",
      "on_hit": "KND",
      "on_ch": "KND"
    },
    {
      "notation": "TRT 3, U",
      "hit_level": "m",
      "damage": "21",
      "speed": "14(44~)",
      "on_block": "-17",
      "on_hit": "KND",
      "on_ch": "KND"
    },
    {
      "notation": "TRT 3, D",
      "hit_level": "m, (MNT)",
      "damage": "21",
      "speed": "14(44~)",
      "on_block": "-14",
      "on_hit": "KND",
      "on_ch": "KND"
    },
    {
      "notation": "TRT 4",
      "hit_level": "m, (MNT)",
      "damage": "24",
      "speed": "27(57~)",
      "on_block": "-24",
      "on_hit": "-6",
      "on_ch": "-6 OC"
    },
    {
      "notation": "TRT 4, d",
      "hit_level": "m, (TRT)",
      "damage": "24",
      "speed": "27 Air(57~)",
      "on_block": "-22",
      "on_hit": "-4",
      "on_ch": "-4 OC"
    },
    {
      "notation": "TRT 4, 3",
      "hit_level": "m, m",
      "damage": "24,20",
      "speed": "27(57~)",
      "on_block": "-14~-12",
      "on_hit": "KND",
      "on_ch": "KND"
    },
    {
      "notation": "TRT 1+2",
      "hit_level": "mm (TJ)",
      "damage": "12,27",
      "speed": "19,29 (49~)",
      "on_block": "-13 OC",
      "on_hit": "KND",
      "on_ch": "KND"
    },
    {
      "notation": "TRT d+1+2",
      "hit_level": "l, (MNT)",
      "damage": "27",
      "speed": "25(55~)",
      "on_block": "-21",
      "on_hit": "KND",
      "on_ch": "KND"
    },
    {
      "notation": "3+4 or WS+3+4 or From certain moves (to SCR)",
      "hit_level": "(SCR)",
      "damage": null,
      "speed": "25(55~)",
      "on_block": null,
      "on_hit": null,
      "on_ch": null
    },
    {
      "notation": "3+4, d/b or u/b or u or U/F (Cancel)",
      "hit_level": "(Special)",
      "damage": null,
      "speed": "25(55~)",
      "on_block": null,
      "on_hit": null,
      "on_ch": null
    },
    {
      "notation": "SCR 1",
      "hit_level": "h, (SCR)",
      "damage": "16",
      "speed": "10(30~)",
      "on_block": "-3",
      "on_hit": "+8",
      "on_ch": "+8"
    },
    {
      "notation": "SCR 2",
      "hit_level": "m, (SCR)",
      "damage": "22",
      "speed": "14(34~)",
      "on_block": "-7",
      "on_hit": "+7",
      "on_ch": "CS"
    },
    {
      "notation": "SCR 2, 2",
      "hit_level": "m, m",
      "damage": "22,22",
      "speed": "14(34~)",
      "on_block": "-10",
      "on_hit": "+8 OC",
      "on_ch": "KND"
    },
    {
      "notation": "SCR 3",
      "hit_level": "m, (SCR)",
      "damage": "20",
      "speed": "13(33~)",
      "on_block": "-6",
      "on_hit": "+5",
      "on_ch": "+5"
    },
    {
      "notation": "SCR 3, 3",
      "hit_level": "m, m, (SCR)",
      "damage": "20,13",
      "speed": "13(33~)",
      "on_block": "-9",
      "on_hit": "+2",
      "on_ch": "+7"
    },
    {
      "notation": "SCR 3, 3, 4",
      "hit_level": "m, m, l (TC)",
      "damage": "20,13,20",
      "speed": "13(33~)",
      "on_block": "-25",
      "on_hit": "KND",
      "on_ch": "KND"
    },
    {
      "notation": "SCR 3, 3, 4, D",
      "hit_level": "m, m, l (TC), (MNT)",
      "damage": "20,13,20",
      "speed": "13(33~)",
      "on_block": "-18",
      "on_hit": "KND",
      "on_ch": "KND"
    },
    {
      "notation": "SCR 3, f+3",
      "hit_level": "m, h, (SCR)",
      "damage": "20,18",
      "speed": "13(33~)",
      "on_block": "-3",
      "on_hit": "KND",
      "on_ch": "KND"
    },
    {
      "notation": "SCR 4",
      "hit_level": "m, (SCR)",
      "damage": "33",
      "speed": "14(34~)",
      "on_block": "-13",
      "on_hit": "Launch (JG?)",
      "on_ch": "Launch (JG?)"
    },
    {
      "notation": "SCR 4, B",
      "hit_level": "m",
      "damage": "33",
      "speed": "14(34~)",
      "on_block": "-18",
      "on_hit": "Launch (JG?)",
      "on_ch": "Launch (JG?)"
    },
    {
      "notation": "SCR 1+2",
      "hit_level": "m",
      "damage": "37",
      "speed": "17~19 (37~)",
      "on_block": "+6~+8",
      "on_hit": "KND",
      "on_ch": "KND"
    },
    {
      "notation": "SCR 1+2, D",
      "hit_level": "m, (TRT)",
      "damage": "37",
      "speed": "17~19 Air (37~)",
      "on_block": "+6~+8",
      "on_hit": "KND",
      "on_ch": "KND"
    },
    {
      "notation": "SCR 3+4",
      "hit_level": "mm (TJ)",
      "damage": "8,18",
      "speed": "17,24~26 (37~)",
      "on_block": "-12~-10",
      "on_hit": "KND",
      "on_ch": "KND"
    },
    {
      "notation": "SCR 3+4, D",
      "hit_level": "mm (TJ), (MNT)",
      "damage": "8,18",
      "speed": "17,24~26 (37~)",
      "on_block": "-13~-11",
      "on_hit": "KND",
      "on_ch": "KND"
    },
    {
      "notation": "SCR d/f+3",
      "hit_level": "l (TC)",
      "damage": "27",
      "speed": "28~29 RC (48~)",
      "on_block": "-21",
      "on_hit": "KND",
      "on_ch": "KND"
    },
    {
      "notation": "SCR d/f+3, d",
      "hit_level": "l (TC), (MNT)",
      "damage": "27",
      "speed": "28~29",
      "on_block": null,
      "on_hit": "KND",
      "on_ch": "KND"
    },
    {
      "notation": "SCR d/f+4",
      "hit_level": "l",
      "damage": "20",
      "speed": "19(39~)",
      "on_block": "-14",
      "on_hit": "+3 OC",
      "on_ch": "KND"
    },
    {
      "notation": "SCR d/f+4, D",
      "hit_level": "l, (MNT)",
      "damage": "20",
      "speed": "19(39~)",
      "on_block": "-14",
      "on_hit": "+3 OC",
      "on_ch": "KND"
    },
    {
      "notation": "SCR d+3",
      "hit_level": "l, (SCR)",
      "damage": "13",
      "speed": "18(38~)",
      "on_block": "-6",
      "on_hit": "-3",
      "on_ch": "+10 OC"
    },
    {
      "notation": "SCR d+3, 3",
      "hit_level": "l, h, (SCR)",
      "damage": "13,37",
      "speed": "18(38~)",
      "on_block": "0 OS",
      "on_hit": "KND",
      "on_ch": "KND"
    },
    {
      "notation": "SCR d+3, 3, B",
      "hit_level": "l, h",
      "damage": "13,37",
      "speed": "18(38~)",
      "on_block": "-1 OS",
      "on_hit": "KND",
      "on_ch": "KND"
    },
    {
      "notation": "SCR d+3, d+3",
      "hit_level": "l, l(SCR)",
      "damage": "13,20",
      "speed": "18(38~)",
      "on_block": "-8",
      "on_hit": "+8 OC",
      "on_ch": "+8 OC"
    },
    {
      "notation": "SCR d+4",
      "hit_level": "l",
      "damage": "27",
      "speed": "26~32 RC (46~)",
      "on_block": "-30~-24",
      "on_hit": "KND",
      "on_ch": "KND"
    },
    {
      "notation": "SCR d+4, D",
      "hit_level": "l, (MNT)",
      "damage": "27",
      "speed": "26~32 (46~)",
      "on_block": "-29~-23",
      "on_hit": "KND",
      "on_ch": "KND"
    },
    {
      "notation": "SCR d+3+4",
      "hit_level": "(SCR)",
      "damage": null,
      "speed": "26~32 (46~)",
      "on_block": null,
      "on_hit": null,
      "on_ch": null
    },
    {
      "notation": "d+3+4 or u/b, b+3+4 or From certain moves (to MNT)",
      "hit_level": "(MNT)",
      "damage": null,
      "speed": "( Air)",
      "on_block": null,
      "on_hit": null,
      "on_ch": null
    },
    {
      "notation": "MNT d/b or u/b or u or U/F (Cancel)",
      "hit_level": "(Special)",
      "damage": null,
      "speed": "()",
      "on_block": null,
      "on_hit": null,
      "on_ch": null
    },
    {
      "notation": "MNT 2+3",
      "hit_level": "(Special)(RBT)(MNT)",
      "damage": null,
      "speed": "RBT",
      "on_block": null,
      "on_hit": null,
      "on_ch": null
    },
    {
      "notation": "MNT 1",
      "hit_level": "m",
      "damage": "16",
      "speed": "13(43~)",
      "on_block": "-7",
      "on_hit": "+5",
      "on_ch": "+5"
    },
    {
      "notation": "MNT 2",
      "hit_level": "m, (MNT)",
      "damage": "25",
      "speed": "13(43~)",
      "on_block": "-15",
      "on_hit": "-4",
      "on_ch": "CS"
    },
    {
      "notation": "MNT 2, 1",
      "hit_level": "m, m, (MNT)",
      "damage": "25,13",
      "speed": "13(43~)",
      "on_block": "-17",
      "on_hit": "-6",
      "on_ch": "-6"
    },
    {
      "notation": "MNT 2, 1, 4",
      "hit_level": "m, m, m, (MNT)",
      "damage": "25,13,33",
      "speed": "13(43~)",
      "on_block": "-13",
      "on_hit": "KND",
      "on_ch": "KND"
    },
    {
      "notation": "MNT 3",
      "hit_level": "l (TC), (MNT)",
      "damage": "25",
      "speed": "22(52~)",
      "on_block": "-14",
      "on_hit": "+3 OC",
      "on_ch": "KND"
    },
    {
      "notation": "MNT 3, 4",
      "hit_level": "l (TC), l (TC), (MNT)",
      "damage": "25,13",
      "speed": "22(52~)",
      "on_block": "-17",
      "on_hit": "-1",
      "on_ch": "-1"
    },
    {
      "notation": "MNT 3, 4, 4",
      "hit_level": "l (TC), l (TC), m (TJ)",
      "damage": "25,13,24",
      "speed": "22(52~) RC",
      "on_block": "-18~-17 OC",
      "on_hit": "-5~-4 OC",
      "on_ch": "KND"
    },
    {
      "notation": "MNT 3, 4, d+4",
      "hit_level": "l (TC), l (TC), l (TC), (MNT)",
      "damage": "25,13,21",
      "speed": "22(52~)",
      "on_block": "-24",
      "on_hit": "+9",
      "on_ch": "+9"
    },
    {
      "notation": "MNT 4",
      "hit_level": "l, (MNT)",
      "damage": "17",
      "speed": "17(47~)",
      "on_block": "-19",
      "on_hit": "-3",
      "on_ch": "+7"
    },
    {
      "notation": "MNT 4, 3",
      "hit_level": "l, m, (MNT)",
      "damage": "17,27",
      "speed": "17(47~)",
      "on_block": "-34",
      "on_hit": "Launch",
      "on_ch": "Launch"
    },
    {
      "notation": "MNT d/f+2",
      "hit_level": "m",
      "damage": "22",
      "speed": "19~20 (49~)",
      "on_block": "-14~-13",
      "on_hit": "Launch",
      "on_ch": "Launch"
    },
    {
      "notation": "MNT d/f+3",
      "hit_level": "m (TJ), (MNT)",
      "damage": "27",
      "speed": "15~16 Air (45~)",
      "on_block": "-17~-16",
      "on_hit": "+11~+12",
      "on_ch": "KND"
    },
    {
      "notation": "MNT d/f+3, 4",
      "hit_level": "m (TJ), (MNT)",
      "damage": "27",
      "speed": "15~16 Air  RBT (45~)",
      "on_block": "-14~-13",
      "on_hit": "+14~+15",
      "on_ch": "KND"
    },
    {
      "notation": "MNT d+1",
      "hit_level": "l, (MNT)",
      "damage": "18",
      "speed": "15(45~)",
      "on_block": "-11",
      "on_hit": "0",
      "on_ch": "0"
    },
    {
      "notation": "MNT d+1, 4",
      "hit_level": "l, m",
      "damage": "18,31",
      "speed": "15(45~)",
      "on_block": "-16",
      "on_hit": "KND",
      "on_ch": "KND"
    },
    {
      "notation": "MNT d+3",
      "hit_level": "l, (MNT)",
      "damage": "16",
      "speed": "15(45~)",
      "on_block": "-12",
      "on_hit": "-1",
      "on_ch": "-1"
    },
    {
      "notation": "MNT d+3, 1",
      "hit_level": "l, m, (MNT)",
      "damage": "16,21",
      "speed": "15(45~)",
      "on_block": "-9",
      "on_hit": "KND",
      "on_ch": "KND"
    },
    {
      "notation": "MNT d+4",
      "hit_level": "l (TC)",
      "damage": "25",
      "speed": "20~23 (50~)",
      "on_block": "-24~-21",
      "on_hit": "+2~+5 OC",
      "on_ch": "KND"
    },
    {
      "notation": "MNT d+4, D",
      "hit_level": "l (TC), (MNT)",
      "damage": "25",
      "speed": "20~23 (50~)",
      "on_block": "-23~-20",
      "on_hit": "+3~+6 OC",
      "on_ch": "KND"
    },
    {
      "notation": "MNT u/f+3",
      "hit_level": "m (TJ)",
      "damage": "33",
      "speed": "26~28 RC (56~)",
      "on_block": "-10~-8 OC",
      "on_hit": "KND",
      "on_ch": "KND"
    },
    {
      "notation": "MNT u/f+3, D",
      "hit_level": "m (TJ), (MNT)",
      "damage": "33",
      "speed": "26~28 (56~)",
      "on_block": "-10~-8 OC",
      "on_hit": "KND",
      "on_ch": "KND"
    }
  ],
  "metadata": {
    "ver": "0.4",
    "game": "ttt2",
    "character": "zafina",
    "type": "normal"
  }
}
